ibridges_servers_uu-0.3.0.dist-info/licenses/LICENSE
ibridgescontrib/uutemplate/__init__.py
ibridgescontrib/uutemplate/templates.py
ibridges_servers_uu-0.3.0.dist-info/METADATA
ibridges_servers_uu-0.3.0.dist-info/WHEEL
ibridges_servers_uu-0.3.0.dist-info/entry_points.txt
ibridges_servers_uu-0.3.0.dist-info/top_level.txt
ibridges_servers_uu-0.3.0.dist-info/RECORD
