Metadata-Version: 2.4
Name: ibridges-servers-uu
Version: 0.3.0
Summary: iRODS environments for connecting to Utrecht University YoDa servers
Author-email: Raoul Schram <r.d.schram@uu.nl>
License: MIT
Classifier: Programming Language :: Python :: 3.8
Classifier: Programming Language :: Python :: 3.9
Classifier: Programming Language :: Python :: 3.10
Classifier: Programming Language :: Python :: 3.11
Classifier: Programming Language :: Python :: 3.12
Classifier: License :: OSI Approved :: MIT License
Requires-Python: >=3.8
License-File: LICENSE
Requires-Dist: ibridges
Provides-Extra: test
Requires-Dist: ruff; extra == "test"
Requires-Dist: mypy; extra == "test"
Dynamic: license-file
